geniux/__init__.py
geniux/aio.py
geniux/base.py
geniux/client.py
geniux/config.py
geniux/utils.py
geniux/version.py
geniux/webClient.py
geniux/enums/__init__.py
geniux/enums/color.py
geniux/enums/language.py
geniux/enums/role.py
geniux/enums/sort.py
geniux/enums/textFormat.py
geniux/errors/__init__.py
geniux/errors/accessDenied.py
geniux/errors/error.py
geniux/errors/geniusInvalidToken.py
geniux/errors/invalidMethod.py
geniux/errors/invalidProxyDict.py
geniux/errors/invalidProxyType.py
geniux/errors/needsTrackIdOrTrackParameter.py
geniux/errors/needsTrackIdOrTrackParameterNotBoth.py
geniux/errors/noneQuery.py
geniux/errors/sessionAlreadyClosed.py
geniux/errors/sessionAlreadyOpened.py
geniux/errors/sessionClosed.py
geniux/errors/tooHighRequestSendingRate.py
geniux/errors/unknown.py
geniux/methods/__init__.py
geniux/methods/albums/__init__.py
geniux/methods/albums/getAlbum.py
geniux/methods/albums/getAlbumTracks.py
geniux/methods/annotations/__init__.py
geniux/methods/annotations/getAnnotation.py
geniux/methods/artists/__init__.py
geniux/methods/artists/getArtist.py
geniux/methods/artists/getArtistAlbums.py
geniux/methods/artists/getArtistTracks.py
geniux/methods/charts/__init__.py
geniux/methods/searching/__init__.py
geniux/methods/searching/_search.py
geniux/methods/searching/search.py
geniux/methods/searching/searchAlbums.py
geniux/methods/searching/searchArtists.py
geniux/methods/searching/searchTracks.py
geniux/methods/searching/searchUsers.py
geniux/methods/tracks/__init__.py
geniux/methods/tracks/getLyrics.py
geniux/methods/tracks/getTrack.py
geniux/methods/tracks/getTrackAnnotations.py
geniux/methods/users/__init__.py
geniux/methods/users/getUser.py
geniux/methods/users/getUserActivities.py
geniux/methods/users/getUserAnnotations.py
geniux/methods/users/getUserComments.py
geniux/methods/users/getUserPyongs.py
geniux/methods/users/getUserQuestionsAndAnswers.py
geniux/methods/users/getUserTranscribes.py
geniux/types/__init__.py
geniux/types/album.py
geniux-0.1.0.dist-info/METADATA
geniux-0.1.0.dist-info/WHEEL
geniux-0.1.0.dist-info/top_level.txt
geniux-0.1.0.dist-info/RECORD
