Metadata-Version: 2.1
Name: geniux
Version: 0.1.0
Summary: Библиотека для взаимодействия с Genius.
Home-page: https://github.com/to4no4sv/geniux
Author: thswq
Author-email: admin@vkmusix.ru
Classifier: Programming Language :: Python :: 3
Classifier: License :: OSI Approved :: GNU Lesser General Public License v3 (LGPLv3)
Classifier: Operating System :: OS Independent
Requires-Python: >=3.6
Requires-Dist: pytz (==2024.1)
Requires-Dist: httpx (==0.27.0)
